Metadata-Version: 2.1
Name: rickrollme
Version: 420.69.666.420
Summary: What could this be???
Home-page: https://www.youtube.com/watch?v=dQw4w9WgXcQ
Author: Richard Astley
Author-email: rick.astley@gmail.com
Requires-Dist: ascvid
